sample
piano
