Metadata-Version: 1.0
Name: piano
Version: 0.3
Summary: CMS built using Pyramid and MongoDB
Home-page: https://github.com/kjq/piano
Author: KimJohn Quinn
Author-email: kjq@logicdrop.com
License: UNKNOWN
Keywords: pyramid mongodb beaker buildout cms
Platform: UNKNOWN
Classifier: Development Status :: 3 - Alpha
Classifier: Environment :: Web Environment
Classifier: Framework :: Pylons
Classifier: Framework :: Buildout
Classifier: Intended Audience :: Developers
Classifier: Intended Audience :: End Users/Desktop
Classifier: Operating System :: MacOS :: MacOS X
Classifier: Operating System :: Microsoft :: Windows
Classifier: Programming Language :: Python :: 2.7
Classifier: Topic :: Internet :: WWW/HTTP
Classifier: Topic :: Internet :: WWW/HTTP :: WSGI :: Application
Classifier: Topic :: Office/Business
